borea_python/__init__.py
borea_python/cli.py
borea_python/config_parser.py
borea_python/content_loader.py
borea_python/file_writer.py
borea_python/generate_method_metadata.py
borea_python/generator.py
borea_python/helpers.py
borea_python/logger.py
borea_python/openapi_parser.py
borea_python/path_validator.py
borea_python/x_code_sample_generator.py
borea_python/models/__init__.py
borea_python/models/borea_config_models.py
borea_python/models/handler_class_models.py
borea_python/models/openapi_models.py
borea_python/models/schema_model.py
borea_python/models/sdk_class_models.py
borea_python/models/tag_class_models.py
borea_python/models/x_code_samples_models.py
borea_python/templates/README.md.jinja
borea_python/templates/base.jinja
borea_python/templates/handler_class.py.jinja
borea_python/templates/requirements.txt.jinja
borea_python/templates/schema.py.jinja
borea_python/templates/sdk_class.py.jinja
borea_python/templates/tag_class.py.jinja
borea_python/templates/test_client.py.jinja
borea_python-1.1.3.dist-info/METADATA
borea_python-1.1.3.dist-info/WHEEL
borea_python-1.1.3.dist-info/licenses/LICENSE
borea_python-1.1.3.dist-info/RECORD
