Metadata-Version: 2.4
Name: borea_python
Version: 1.1.3
Summary: Generate extensible python HTTP client from OpenAPI spec
Project-URL: Homepage, https://github.com/Borea-dev/python-client-generator
Project-URL: Issues, https://github.com/Borea-dev/python-client-generator/issues
Author-email: David Bauch <pypi@borea.dev>
License: MIT
License-File: LICENSE
Keywords: Borea,Client,Generator,OpenAPI
Classifier: Development Status :: 4 - Beta
Classifier: Intended Audience :: Developers
Classifier: License :: OSI Approved :: MIT License
Classifier: Programming Language :: Python :: 3
Classifier: Programming Language :: Python :: 3.9
Classifier: Programming Language :: Python :: 3.10
Classifier: Programming Language :: Python :: 3.11
Classifier: Programming Language :: Python :: 3.12
Classifier: Programming Language :: Python :: 3.13
Classifier: Topic :: Software Development :: Code Generators
Classifier: Typing :: Typed
Requires-Python: <4.0,>=3.9
Requires-Dist: click<9.0.0,>=8.0.0
Requires-Dist: datamodel-code-generator<1.0.0,>=0.28.0
Requires-Dist: httpx<0.28.0,>=0.20.0
Requires-Dist: jinja2<4.0.0,>=3.0.0
Requires-Dist: pydantic<3.0.0,>=2.0.0
Requires-Dist: pyyaml<7.0,>=6.0
Requires-Dist: ruff<0.3,>=0.2
